fese/__init__.py
fese/container.py
fese/disposition.py
fese/exceptions.py
fese/stream.py
fese/tags.py
fese-0.2.7.dist-info/LICENSE
fese-0.2.7.dist-info/METADATA
fese-0.2.7.dist-info/WHEEL
fese-0.2.7.dist-info/top_level.txt
fese-0.2.7.dist-info/RECORD
